ellipsinator/__init__.py
ellipsinator/_fit_ellipse_process_params.py
ellipsinator/basic.py
ellipsinator/direct_ellipse_fit.py
ellipsinator/fast_guaranteed_ellipse_estimate.py
ellipsinator/fit_ellipse_fitzgibon.py
ellipsinator/fit_ellipse_halir.py
ellipsinator/_fast_guaranteed_ellipse_funcs/__init__.py
ellipsinator/_fast_guaranteed_ellipse_funcs/compute_directellipse_estimate.py
ellipsinator/_fast_guaranteed_ellipse_funcs/fastGuaranteedEllipseFit.py
ellipsinator/_fast_guaranteed_ellipse_funcs/fastLevenbergMarquardtStep.py
ellipsinator/_fast_guaranteed_ellipse_funcs/normalize_data_isotropically.py
ellipsinator/_fast_guaranteed_ellipse_funcs/struct_t.py
ellipsinator/tests/fgee_test_data.py
ellipsinator/tests/test_fast_guaranteed_ellipse_estimate.py
ellipsinator/tests/test_fit_ellipse_halir.py
ellipsinator-0.3.0.dist-info/LICENSE
ellipsinator-0.3.0.dist-info/METADATA
ellipsinator-0.3.0.dist-info/WHEEL
ellipsinator-0.3.0.dist-info/top_level.txt
ellipsinator-0.3.0.dist-info/RECORD
