Metadata-Version: 2.1
Name: ellipsinator
Version: 0.3.0
Summary: Ellipse tools for Python
Author-email: Nicholas McKibben <nicholas.bgp@gmail.com>
Maintainer-email: Nicholas McKibben <nicholas.bgp@gmail.com>
License: Copyright (c) 2023 Nicholas McKibben
Project-URL: Homepage, https://github.com/mckib2/ellipsinator
Requires-Python: >=3.8
License-File: LICENSE
Requires-Dist: numpy >=1.26.1
